tsmaker/__init__.py
tsmaker/argument_parsing.py
tsmaker/cli.py
tsmaker/distribution.py
tsmaker/generators/__init__.py
tsmaker/generators/apartment.py
tsmaker/generators/arima.py
tsmaker/generators/fourier.py
tsmaker/generators/grocery_sales.py
tsmaker/generators/random.py
tsmaker/generators/random_walk.py
tsmaker/generators/stock_market.py
tsmaker/maker_settings.py
tsmaker/persistence/__init__.py
tsmaker/persistence/arrow_data_set.py
tsmaker/persistence/csv.py
tsmaker/persistence/delta_lake.py
tsmaker/persistence/file_persistence.py
tsmaker/persistence/iceberg.py
tsmaker/persistence/influx.py
tsmaker/persistence/parquet.py
tsmaker/persistence/persistence.py
tsmaker/persistence/tsv.py
tsmaker/plotting.py
tsmaker/utils.py
tsmaker-0.1.9.dist-info/licenses/LICENSE
tsmaker-0.1.9.dist-info/WHEEL
tsmaker-0.1.9.dist-info/entry_points.txt
tsmaker-0.1.9.dist-info/METADATA
tsmaker-0.1.9.dist-info/RECORD
